pywavelink/__init__.py
pywavelink/__main__.py
pywavelink/backoff.py
pywavelink/enums.py
pywavelink/exceptions.py
pywavelink/filters.py
pywavelink/node.py
pywavelink/payloads.py
pywavelink/player.py
pywavelink/queue.py
pywavelink/tracks.py
pywavelink/websocket.py
pywavelink/ext/spotify/__init__.py
pywavelink/ext/spotify/utils.py
pywavelink/types/events.py
pywavelink/types/request.py
pywavelink/types/state.py
pywavelink/types/track.py
pywavelink-2.6.5.dist-info/LICENSE
pywavelink-2.6.5.dist-info/METADATA
pywavelink-2.6.5.dist-info/WHEEL
pywavelink-2.6.5.dist-info/top_level.txt
pywavelink-2.6.5.dist-info/RECORD
