Metadata-Version: 2.1
Name: pywavelink
Version: 2.6.5
Summary: A robust and powerful Lavalink wrapper for py-cord
Author: Timo
Project-URL: Homepage, https://github.com/PythonistaGuild/Wavelink
Classifier: License :: OSI Approved :: MIT License
Classifier: Intended Audience :: Developers
Classifier: Natural Language :: English
Classifier: Operating System :: OS Independent
Classifier: Programming Language :: Python :: 3.10
Classifier: Programming Language :: Python :: 3.11
Classifier: Programming Language :: Python :: 3.12
Classifier: Topic :: Internet
Classifier: Topic :: Software Development :: Libraries
Classifier: Topic :: Software Development :: Libraries :: Python Modules
Classifier: Topic :: Utilities
Requires-Python: >=3.10
License-File: LICENSE
Requires-Dist: aiohttp <4,>=3.7.4
Requires-Dist: yarl ~=1.8.2
